cloe_api/__init__.py
cloe_api/main.py
cloe_api/py.typed
cloe_api/api/__init__.py
cloe_api/api/api_v1/__init__.py
cloe_api/api/api_v1/api.py
cloe_api/api/api_v1/endpoints/__init__.py
cloe_api/api/api_v1/endpoints/crawler.py
cloe_api/api/api_v1/endpoints/dataflow.py
cloe_api/api/api_v1/endpoints/exec_sql.py
cloe_api/api/api_v1/endpoints/full_model.py
cloe_api/api/api_v1/endpoints/repository.py
cloe_api/utils/__init__.py
cloe_api/utils/create_db_model_file_structure.py
cloe_api-0.1.15.dist-info/METADATA
cloe_api-0.1.15.dist-info/WHEEL
cloe_api-0.1.15.dist-info/RECORD
