Metadata-Version: 2.4
Name: cloe-api
Version: 0.1.15
Summary: The API wraps most CLOE functions conveniently for the GUI.
Author-email: initions <ICSMC_EXT_PYPIORG@accenture.com>
License: MIT
Classifier: Development Status :: 5 - Production/Stable
Classifier: Environment :: Console
Classifier: Intended Audience :: Developers
Classifier: License :: OSI Approved :: MIT License
Classifier: Operating System :: OS Independent
Classifier: Programming Language :: Python :: 3
Classifier: Topic :: Database
Requires-Python: <3.12,>=3.11
Requires-Dist: cloe-metadata-to-ddl~=1.1.4
Requires-Dist: cloe-metadata~=2.2.1
Requires-Dist: cloe-snowflake-crawler~=1.1.1
Requires-Dist: cloe-sql-transformations~=1.0.11
Requires-Dist: cloe-util-snowflake-connector~=1.0.2
Requires-Dist: fastapi~=0.116.0
Requires-Dist: uvicorn~=0.35.0
